[{"fields": {"move_effect": null, "power": null, "move": 2, "pp": null, "move_effect_chance": null, "type": 1, "version_group": 3, "accuracy": null}, "model": "pokemon_v2.movechange", "pk": 1}, {"fields": {"move_effect": null, "power": null, "move": 13, "pp": null, "move_effect_chance": null, "type": null, "version_group": 5, "accuracy": 75}, "model": "pokemon_v2.movechange", "pk": 2}, {"fields": {"move_effect": 1, "power": null, "move": 16, "pp": null, "move_effect_chance": null, "type": 1, "version_group": 3, "accuracy": null}, "model": "pokemon_v2.movechange", "pk": 3}, {"fields": {"move_effect": null, "power": 35, "move": 17, "pp": null, "move_effect_chance": null, "type": null, "version_group": 3, "accuracy": null}, "model": "pokemon_v2.movechange", "pk": 4}, {"fields": {"move_effect": null, "power": null, "move": 18, "pp": null, "move_effect_chance": null, "type": null, "version_group": 3, "accuracy": 85}, "model": "pokemon_v2.movechange", "pk": 5}, {"fields": {"move_effect": null, "power": 70, "move": 19, "pp": null, "move_effect_chance": null, "type": null, "version_group": 8, "accuracy": null}, "model": "pokemon_v2.movechange", "pk": 6}, {"fields": {"move_effect": null, "power": null, "move": 20, "pp": null, "move_effect_chance": null, "type": null, "version_group": 11, "accuracy": 75}, "model": "pokemon_v2.movechange", "pk": 7}, {"fields": {"move_effect": null, "power": null, "move": 22, "pp": 10, "move_effect_chance": null, "type": null, "version_group": 8, "accuracy": null}, "model": "pokemon_v2.movechange", "pk": 8}, {"fields": {"move_effect": null, "power": 70, "move": 26, "pp": null, "move_effect_chance": null, "type": null, "version_group": 8, "accuracy": null}, "model": "pokemon_v2.movechange", "pk": 9}, {"fields": {"move_effect": null, "power": 85, "move": 26, "pp": 25, "move_effect_chance": null, "type": null, "version_group": 11, "accuracy": null}, "model": "pokemon_v2.movechange", "pk": 10}, {"fields": {"move_effect": null, "power": null, "move": 28, "pp": null, "move_effect_chance": null, "type": 1, "version_group": 3, "accuracy": null}, "model": "pokemon_v2.movechange", "pk": 11}, {"fields": {"move_effect": null, "power": 35, "move": 33, "pp": null, "move_effect_chance": null, "type": null, "version_group": 11, "accuracy": 95}, "model": "pokemon_v2.movechange", "pk": 12}, {"fields": {"move_effect": null, "power": null, "move": 35, "pp": null, "move_effect_chance": null, "type": null, "version_group": 11, "accuracy": 85}, "model": "pokemon_v2.movechange", "pk": 13}, {"fields": {"move_effect": null, "power": 90, "move": 37, "pp": 20, "move_effect_chance": null, "type": null, "version_group": 11, "accuracy": null}, "model": "pokemon_v2.movechange", "pk": 14}, {"fields": {"move_effect": 49, "power": 100, "move": 38, "pp": null, "move_effect_chance": null, "type": null, "version_group": 3, "accuracy": null}, "model": "pokemon_v2.movechange", "pk": 15}, {"fields": {"move_effect": null, "power": null, "move": 40, "pp": null, "move_effect_chance": 20, "type": null, "version_group": 3, "accuracy": null}, "model": "pokemon_v2.movechange", "pk": 16}, {"fields": {"move_effect": null, "power": null, "move": 44, "pp": null, "move_effect_chance": 10, "type": 1, "version_group": 3, "accuracy": null}, "model": "pokemon_v2.movechange", "pk": 17}, {"fields": {"move_effect": null, "power": null, "move": 50, "pp": null, "move_effect_chance": null, "type": null, "version_group": 8, "accuracy": 55}, "model": "pokemon_v2.movechange", "pk": 18}, {"fields": {"move_effect": null, "power": null, "move": 50, "pp": null, "move_effect_chance": null, "type": null, "version_group": 11, "accuracy": 80}, "model": "pokemon_v2.movechange", "pk": 19}, {"fields": {"move_effect": null, "power": null, "move": 59, "pp": null, "move_effect_chance": null, "type": null, "version_group": 3, "accuracy": 90}, "model": "pokemon_v2.movechange", "pk": 20}, {"fields": {"move_effect": 32, "power": 50, "move": 67, "pp": null, "move_effect_chance": 30, "type": null, "version_group": 5, "accuracy": 90}, "model": "pokemon_v2.movechange", "pk": 21}, {"fields": {"move_effect": null, "power": null, "move": 71, "pp": 20, "move_effect_chance": null, "type": null, "version_group": 8, "accuracy": null}, "model": "pokemon_v2.movechange", "pk": 22}, {"fields": {"move_effect": null, "power": null, "move": 72, "pp": 10, "move_effect_chance": null, "type": null, "version_group": 8, "accuracy": null}, "model": "pokemon_v2.movechange", "pk": 23}, {"fields": {"move_effect": 14, "power": null, "move": 74, "pp": null, "move_effect_chance": null, "type": null, "version_group": 11, "accuracy": null}, "model": "pokemon_v2.movechange", "pk": 24}, {"fields": {"move_effect": null, "power": 70, "move": 80, "pp": null, "move_effect_chance": null, "type": null, "version_group": 8, "accuracy": null}, "model": "pokemon_v2.movechange", "pk": 25}, {"fields": {"move_effect": null, "power": 90, "move": 80, "pp": 20, "move_effect_chance": null, "type": null, "version_group": 11, "accuracy": null}, "model": "pokemon_v2.movechange", "pk": 26}, {"fields": {"move_effect": null, "power": 15, "move": 83, "pp": null, "move_effect_chance": null, "type": null, "version_group": 11, "accuracy": 70}, "model": "pokemon_v2.movechange", "pk": 27}, {"fields": {"move_effect": null, "power": null, "move": 87, "pp": null, "move_effect_chance": 10, "type": null, "version_group": 3, "accuracy": null}, "model": "pokemon_v2.movechange", "pk": 28}, {"fields": {"move_effect": null, "power": null, "move": 88, "pp": null, "move_effect_chance": null, "type": null, "version_group": 3, "accuracy": 65}, "model": "pokemon_v2.movechange", "pk": 29}, {"fields": {"move_effect": null, "power": 100, "move": 91, "pp": null, "move_effect_chance": null, "type": null, "version_group": 3, "accuracy": null}, "model": "pokemon_v2.movechange", "pk": 30}, {"fields": {"move_effect": null, "power": 60, "move": 91, "pp": null, "move_effect_chance": null, "type": null, "version_group": 8, "accuracy": null}, "model": "pokemon_v2.movechange", "pk": 31}, {"fields": {"move_effect": null, "power": null, "move": 92, "pp": null, "move_effect_chance": null, "type": null, "version_group": 11, "accuracy": 85}, "model": "pokemon_v2.movechange", "pk": 32}, {"fields": {"move_effect": null, "power": null, "move": 94, "pp": null, "move_effect_chance": 30, "type": null, "version_group": 3, "accuracy": null}, "model": "pokemon_v2.movechange", "pk": 33}, {"fields": {"move_effect": null, "power": null, "move": 95, "pp": null, "move_effect_chance": null, "type": null, "version_group": 8, "accuracy": 60}, "model": "pokemon_v2.movechange", "pk": 34}, {"fields": {"move_effect": null, "power": null, "move": 95, "pp": null, "move_effect_chance": null, "type": null, "version_group": 9, "accuracy": 70}, "model": "pokemon_v2.movechange", "pk": 35}, {"fields": {"move_effect": null, "power": null, "move": 105, "pp": 20, "move_effect_chance": null, "type": null, "version_group": 8, "accuracy": null}, "model": "pokemon_v2.movechange", "pk": 36}, {"fields": {"move_effect": null, "power": 130, "move": 120, "pp": null, "move_effect_chance": null, "type": null, "version_group": 3, "accuracy": null}, "model": "pokemon_v2.movechange", "pk": 37}, {"fields": {"move_effect": null, "power": null, "move": 126, "pp": null, "move_effect_chance": 30, "type": null, "version_group": 3, "accuracy": null}, "model": "pokemon_v2.movechange", "pk": 38}, {"fields": {"move_effect": null, "power": null, "move": 128, "pp": 10, "move_effect_chance": null, "type": null, "version_group": 11, "accuracy": 75}, "model": "pokemon_v2.movechange", "pk": 39}, {"fields": {"move_effect": null, "power": 85, "move": 136, "pp": null, "move_effect_chance": null, "type": null, "version_group": 8, "accuracy": null}, "model": "pokemon_v2.movechange", "pk": 40}, {"fields": {"move_effect": null, "power": 100, "move": 136, "pp": 20, "move_effect_chance": null, "type": null, "version_group": 11, "accuracy": null}, "model": "pokemon_v2.movechange", "pk": 41}, {"fields": {"move_effect": null, "power": null, "move": 137, "pp": null, "move_effect_chance": null, "type": null, "version_group": 11, "accuracy": 75}, "model": "pokemon_v2.movechange", "pk": 42}, {"fields": {"move_effect": null, "power": null, "move": 139, "pp": null, "move_effect_chance": null, "type": null, "version_group": 11, "accuracy": 55}, "model": "pokemon_v2.movechange", "pk": 43}, {"fields": {"move_effect": null, "power": null, "move": 143, "pp": null, "move_effect_chance": 10, "type": null, "version_group": 3, "accuracy": null}, "model": "pokemon_v2.movechange", "pk": 44}, {"fields": {"move_effect": 1, "power": null, "move": 146, "pp": null, "move_effect_chance": 0, "type": null, "version_group": 3, "accuracy": null}, "model": "pokemon_v2.movechange", "pk": 45}, {"fields": {"move_effect": null, "power": null, "move": 148, "pp": null, "move_effect_chance": null, "type": null, "version_group": 8, "accuracy": 70}, "model": "pokemon_v2.movechange", "pk": 46}, {"fields": {"move_effect": null, "power": null, "move": 152, "pp": null, "move_effect_chance": null, "type": null, "version_group": 11, "accuracy": 85}, "model": "pokemon_v2.movechange", "pk": 47}, {"fields": {"move_effect": null, "power": 170, "move": 153, "pp": null, "move_effect_chance": null, "type": null, "version_group": 3, "accuracy": null}, "model": "pokemon_v2.movechange", "pk": 48}, {"fields": {"move_effect": 1, "power": null, "move": 157, "pp": null, "move_effect_chance": 0, "type": null, "version_group": 3, "accuracy": null}, "model": "pokemon_v2.movechange", "pk": 49}, {"fields": {"move_effect": 1, "power": null, "move": 161, "pp": null, "move_effect_chance": 0, "type": null, "version_group": 3, "accuracy": null}, "model": "pokemon_v2.movechange", "pk": 50}, {"fields": {"move_effect": null, "power": null, "move": 170, "pp": 40, "move_effect_chance": null, "type": null, "version_group": 11, "accuracy": null}, "model": "pokemon_v2.movechange", "pk": 51}, {"fields": {"move_effect": null, "power": null, "move": 174, "pp": null, "move_effect_chance": null, "type": 10001, "version_group": 11, "accuracy": null}, "model": "pokemon_v2.movechange", "pk": 52}, {"fields": {"move_effect": null, "power": null, "move": 178, "pp": null, "move_effect_chance": null, "type": null, "version_group": 11, "accuracy": 85}, "model": "pokemon_v2.movechange", "pk": 53}, {"fields": {"move_effect": null, "power": null, "move": 184, "pp": null, "move_effect_chance": null, "type": null, "version_group": 11, "accuracy": 90}, "model": "pokemon_v2.movechange", "pk": 54}, {"fields": {"move_effect": null, "power": 100, "move": 192, "pp": null, "move_effect_chance": null, "type": null, "version_group": 8, "accuracy": null}, "model": "pokemon_v2.movechange", "pk": 55}, {"fields": {"move_effect": null, "power": null, "move": 198, "pp": null, "move_effect_chance": null, "type": null, "version_group": 11, "accuracy": 80}, "model": "pokemon_v2.movechange", "pk": 56}, {"fields": {"move_effect": null, "power": 90, "move": 200, "pp": null, "move_effect_chance": null, "type": null, "version_group": 8, "accuracy": null}, "model": "pokemon_v2.movechange", "pk": 57}, {"fields": {"move_effect": null, "power": null, "move": 200, "pp": 15, "move_effect_chance": null, "type": null, "version_group": 11, "accuracy": null}, "model": "pokemon_v2.movechange", "pk": 58}, {"fields": {"move_effect": null, "power": null, "move": 202, "pp": 5, "move_effect_chance": null, "type": null, "version_group": 8, "accuracy": null}, "model": "pokemon_v2.movechange", "pk": 59}, {"fields": {"move_effect": null, "power": 60, "move": 202, "pp": null, "move_effect_chance": null, "type": null, "version_group": 11, "accuracy": null}, "model": "pokemon_v2.movechange", "pk": 60}, {"fields": {"move_effect": null, "power": 10, "move": 210, "pp": null, "move_effect_chance": null, "type": null, "version_group": 11, "accuracy": null}, "model": "pokemon_v2.movechange", "pk": 61}, {"fields": {"move_effect": null, "power": 80, "move": 248, "pp": 15, "move_effect_chance": null, "type": null, "version_group": 11, "accuracy": 90}, "model": "pokemon_v2.movechange", "pk": 62}, {"fields": {"move_effect": null, "power": 20, "move": 249, "pp": null, "move_effect_chance": null, "type": null, "version_group": 8, "accuracy": null}, "model": "pokemon_v2.movechange", "pk": 63}, {"fields": {"move_effect": null, "power": 15, "move": 250, "pp": null, "move_effect_chance": null, "type": null, "version_group": 11, "accuracy": 70}, "model": "pokemon_v2.movechange", "pk": 64}, {"fields": {"move_effect": null, "power": 10, "move": 251, "pp": null, "move_effect_chance": null, "type": null, "version_group": 11, "accuracy": null}, "model": "pokemon_v2.movechange", "pk": 65}, {"fields": {"move_effect": null, "power": 50, "move": 253, "pp": null, "move_effect_chance": null, "type": null, "version_group": 11, "accuracy": null}, "model": "pokemon_v2.movechange", "pk": 66}, {"fields": {"move_effect": null, "power": null, "move": 254, "pp": 10, "move_effect_chance": null, "type": null, "version_group": 8, "accuracy": null}, "model": "pokemon_v2.movechange", "pk": 67}, {"fields": {"move_effect": null, "power": 60, "move": 291, "pp": null, "move_effect_chance": null, "type": null, "version_group": 8, "accuracy": null}, "model": "pokemon_v2.movechange", "pk": 68}, {"fields": {"move_effect": 54, "power": null, "move": 294, "pp": null, "move_effect_chance": null, "type": null, "version_group": 11, "accuracy": null}, "model": "pokemon_v2.movechange", "pk": 69}, {"fields": {"move_effect": null, "power": 15, "move": 328, "pp": null, "move_effect_chance": null, "type": null, "version_group": 11, "accuracy": 70}, "model": "pokemon_v2.movechange", "pk": 70}, {"fields": {"move_effect": null, "power": 10, "move": 331, "pp": null, "move_effect_chance": null, "type": null, "version_group": 11, "accuracy": null}, "model": "pokemon_v2.movechange", "pk": 71}, {"fields": {"move_effect": null, "power": 10, "move": 333, "pp": null, "move_effect_chance": null, "type": null, "version_group": 11, "accuracy": null}, "model": "pokemon_v2.movechange", "pk": 72}, {"fields": {"move_effect": null, "power": 40, "move": 343, "pp": null, "move_effect_chance": null, "type": null, "version_group": 11, "accuracy": null}, "model": "pokemon_v2.movechange", "pk": 73}, {"fields": {"move_effect": null, "power": 70, "move": 348, "pp": null, "move_effect_chance": null, "type": null, "version_group": 8, "accuracy": null}, "model": "pokemon_v2.movechange", "pk": 74}, {"fields": {"move_effect": null, "power": null, "move": 350, "pp": null, "move_effect_chance": null, "type": null, "version_group": 11, "accuracy": 80}, "model": "pokemon_v2.movechange", "pk": 75}, {"fields": {"move_effect": null, "power": 120, "move": 353, "pp": null, "move_effect_chance": null, "type": null, "version_group": 11, "accuracy": 85}, "model": "pokemon_v2.movechange", "pk": 76}, {"fields": {"move_effect": null, "power": 50, "move": 364, "pp": null, "move_effect_chance": null, "type": null, "version_group": 11, "accuracy": null}, "model": "pokemon_v2.movechange", "pk": 77}, {"fields": {"move_effect": null, "power": 0, "move": 382, "pp": null, "move_effect_chance": null, "type": null, "version_group": 11, "accuracy": null}, "model": "pokemon_v2.movechange", "pk": 78}, {"fields": {"move_effect": null, "power": 60, "move": 386, "pp": null, "move_effect_chance": null, "type": null, "version_group": 11, "accuracy": null}, "model": "pokemon_v2.movechange", "pk": 79}, {"fields": {"move_effect": null, "power": 130, "move": 387, "pp": null, "move_effect_chance": null, "type": null, "version_group": 11, "accuracy": null}, "model": "pokemon_v2.movechange", "pk": 80}, {"fields": {"move_effect": null, "power": 60, "move": 409, "pp": 5, "move_effect_chance": null, "type": null, "version_group": 11, "accuracy": null}, "model": "pokemon_v2.movechange", "pk": 81}, {"fields": {"move_effect": null, "power": null, "move": 463, "pp": null, "move_effect_chance": null, "type": null, "version_group": 11, "accuracy": 70}, "model": "pokemon_v2.movechange", "pk": 82}]
